MANIFEST.in
setup.py
memsink/__init__.py
memsink/memsink.c
memsink/memsink.h
memsink.egg-info/PKG-INFO
memsink.egg-info/SOURCES.txt
memsink.egg-info/dependency_links.txt
memsink.egg-info/not-zip-safe
memsink.egg-info/top_level.txt