Metadata-Version: 1.0
Name: memsink
Version: 0.0.1
Summary: Experimental copy-on-invalidate memory protocol
Home-page: http://github.com/dw/memsink/
Author: David Wilson
Author-email: dw@botanicus.net
License: Apache 2
Platform: UNKNOWN
